mds_mdswordwrap-0.1.0.dist-info/DESCRIPTION.rst
mds_mdswordwrap-0.1.0.dist-info/METADATA
mds_mdswordwrap-0.1.0.dist-info/RECORD
mds_mdswordwrap-0.1.0.dist-info/WHEEL
mds_mdswordwrap-0.1.0.dist-info/metadata.json
mds_mdswordwrap-0.1.0.dist-info/top_level.txt
mdswordwrap/__init__.py
mdswordwrap/libwordwrap.py
